{
  "sources": [
    {
      "title": "Twitter @DeFi Pulse",
      "feedUrl": "https://rsshub.app/twitter/user/defipulse",
      "siteUrl": "https://twitter.com/defipulse",
      "articles": [
        {
          "id": "https://twitter.com/defipulse/status/1624151303617187840",
          "author": "DeFi Pulse",
          "description": "Republican congressmen call out Gary Gensler and request documents surrounding the SEC's interactions with SBF and FTX...\n\nRep. Bill Huizenga: Since @garygensler won't abide by his own polices to \"come in and talk”, the House GOP will hold him accountable. Today, as promised, our oversight of the @SECGov begins with a request for documents surrounding their interactions with @SBF_FTX, @FTX_Official, and @TheJusticeDept",
          "link": "https://twitter.com/defipulse/status/1624151303617187840",
          "publishedOn": "2023-02-10T21:00:20.000Z",
          "wordCount": 492,
          "title": "Republican congressmen call out Gary Gensler and request documents surrounding the SEC's interactions with SBF and FTX...",
          "imageUrl": null
        },
        {
          "id": "https://twitter.com/defipulse/status/1624141142554968064",
          "author": "DeFi Pulse",
          "description": "Re Full statement: https://www.sec.gov/news/statement/peirce-statement-kraken-020923",
          "link": "https://twitter.com/defipulse/status/1624141142554968064",
          "publishedOn": "2023-02-10T20:19:58.000Z",
          "wordCount": 492,
          "title": "Re Full statement:",
          "imageUrl": null
        },
        {
          "id": "https://twitter.com/defipulse/status/1624141141405798439",
          "author": "DeFi Pulse",
          "description": "\"A paternalistic and lazy regulator settles on a solution like the one in this settlement...\"\nSEC Commissioner Hester Peirce criticizing the Kraken enforcement action...",
          "link": "https://twitter.com/defipulse/status/1624141141405798439",
          "publishedOn": "2023-02-10T20:19:57.000Z",
          "wordCount": 492,
          "title": "\"A paternalistic and lazy regulator settles on a solution like the one in this settlement...\" SEC Commissioner Hester Peirce criticizing the Kraken en...",
          "imageUrl": null
        },
        {
          "id": "https://twitter.com/defipulse/status/1623786312628150273",
          "author": "DeFi Pulse",
          "description": "Re “Whether it’s through staking-as-a-service, lending, or other means, crypto intermediaries, when offering investment contracts in exchange for investors’ tokens, need to provide the proper disclosures and safeguards required by our securities laws…”\n- SEC Chair Gary Gensler",
          "link": "https://twitter.com/defipulse/status/1623786312628150273",
          "publishedOn": "2023-02-09T20:50:00.000Z",
          "wordCount": 492,
          "title": "Re “Whether it’s through staking-as-a-service, lending, or other means, crypto intermediaries, when offering investment contracts in exchange for in...",
          "imageUrl": null
        },
        {
          "id": "https://twitter.com/defipulse/status/1623783846331183105",
          "author": "DeFi Pulse",
          "description": "Re  https://blog.kraken.com/post/17619/settlement/",
          "link": "https://twitter.com/defipulse/status/1623783846331183105",
          "publishedOn": "2023-02-09T20:40:12.000Z",
          "wordCount": 492,
          "title": "Re",
          "imageUrl": null
        },
        {
          "id": "https://twitter.com/defipulse/status/1623783842115887105",
          "author": "DeFi Pulse",
          "description": "Re Kraken will continue to offer staking services for non-U.S. clients through a separate Kraken subsidiary.",
          "link": "https://twitter.com/defipulse/status/1623783842115887105",
          "publishedOn": "2023-02-09T20:40:11.000Z",
          "wordCount": 492,
          "title": "Re Kraken will continue to offer staking services for non-U.S. clients through a separate Kraken subsidiary.",
          "imageUrl": null
        },
        {
          "id": "https://twitter.com/defipulse/status/1623783839087616001",
          "author": "DeFi Pulse",
          "description": "Re All U.S. assets will be automatically unstaked except for Ether which will be unstaked after the Shanghai upgrade.",
          "link": "https://twitter.com/defipulse/status/1623783839087616001",
          "publishedOn": "2023-02-09T20:40:10.000Z",
          "wordCount": 492,
          "title": "Re All U.S. assets will be automatically unstaked except for Ether which will be unstaked after the Shanghai upgrade.",
          "imageUrl": null
        },
        {
          "id": "https://twitter.com/defipulse/status/1623783836126519296",
          "author": "DeFi Pulse",
          "description": "Kraken to end on-chain staking services for U.S. clients…",
          "link": "https://twitter.com/defipulse/status/1623783836126519296",
          "publishedOn": "2023-02-09T20:40:09.000Z",
          "wordCount": 492,
          "title": "Kraken to end on-chain staking services for U.S. clients…",
          "imageUrl": null
        },
        {
          "id": "https://twitter.com/defipulse/status/1623779071468400640",
          "author": "DeFi Pulse",
          "description": "Re  https://www.sec.gov/news/press-release/2023-25",
          "link": "https://twitter.com/defipulse/status/1623779071468400640",
          "publishedOn": "2023-02-09T20:21:13.000Z",
          "wordCount": 492,
          "title": "Re",
          "imageUrl": null
        },
        {
          "id": "https://twitter.com/defipulse/status/1623779069740343301",
          "author": "DeFi Pulse",
          "description": "SEC issues press release on Kraken staking settlement...",
          "link": "https://twitter.com/defipulse/status/1623779069740343301",
          "publishedOn": "2023-02-09T20:21:13.000Z",
          "wordCount": 492,
          "title": "SEC issues press release on Kraken staking settlement...",
          "imageUrl": null
        },
        {
          "id": "https://twitter.com/defipulse/status/1623765656066789387",
          "author": "DeFi Pulse",
          "description": "Re  https://www.coindesk.com/policy/2023/02/09/kraken-agreed-to-shutter-crypto-staking-operations-to-settle-sec-charges-source/?utm_content=editorial&utm_medium=social&utm_campaign=coindesk_main&utm_source=twitter&utm_term=organic",
          "link": "https://twitter.com/defipulse/status/1623765656066789387",
          "publishedOn": "2023-02-09T19:27:55.000Z",
          "wordCount": 492,
          "title": "Re",
          "imageUrl": null
        },
        {
          "id": "https://twitter.com/defipulse/status/1623765654154125314",
          "author": "DeFi Pulse",
          "description": "Kraken agrees to shut down crypto-staking operations to settle SEC charges...",
          "link": "https://twitter.com/defipulse/status/1623765654154125314",
          "publishedOn": "2023-02-09T19:27:54.000Z",
          "wordCount": 492,
          "title": "Kraken agrees to shut down crypto-staking operations to settle SEC charges...",
          "imageUrl": null
        },
        {
          "id": "https://twitter.com/defipulse/status/1623460031361437699",
          "author": "DeFi Pulse",
          "description": "Coinbase CEO hearing rumors the SEC would like to get rid of staking for retail customers…\n\nBrian Armstrong: 1/ We're hearing rumors that the SEC would like to get rid of crypto staking in the U.S. for retail customers. I hope that's not the case as I believe it would be a terrible path for the U.S. if that was allowed to happen.",
          "link": "https://twitter.com/defipulse/status/1623460031361437699",
          "publishedOn": "2023-02-08T23:13:28.000Z",
          "wordCount": 492,
          "title": "Coinbase CEO hearing rumors the SEC would like to get rid of staking for retail customers…",
          "imageUrl": null
        },
        {
          "id": "https://twitter.com/defipulse/status/1623398052278026240",
          "author": "DeFi Pulse",
          "description": ".@SenatorHagerty defends crypto, decries using banking regulators to advance political agendas...\n\nSenator Bill Hagerty: Regulators singling out business activities should alarm all Americans. \nIt doesn’t matter if it’s cryptoassets, firearms, or any other lawful business, using banking regulators to advance political agendas should not be tolerated.\n https://blockworks.co/news/crypto-poses-key-risks-to-banks-but-carry-on",
          "link": "https://twitter.com/defipulse/status/1623398052278026240",
          "publishedOn": "2023-02-08T19:07:11.000Z",
          "wordCount": 492,
          "title": ".@SenatorHagerty defends crypto, decries using banking regulators to advance political agendas...",
          "imageUrl": null
        },
        {
          "id": "https://twitter.com/defipulse/status/1622653064527114242",
          "author": "DeFi Pulse",
          "description": "Re  https://www.coindesk.com/business/2023/02/06/crypto-exchange-binance-to-suspend-us-dollar-deposits-this-week/",
          "link": "https://twitter.com/defipulse/status/1622653064527114242",
          "publishedOn": "2023-02-06T17:46:52.000Z",
          "wordCount": 492,
          "title": "Re",
          "imageUrl": null
        },
        {
          "id": "https://twitter.com/defipulse/status/1622653062077718551",
          "author": "DeFi Pulse",
          "description": "Binance to temporarily suspend US dollar bank transfers starting on Wednesday...",
          "link": "https://twitter.com/defipulse/status/1622653062077718551",
          "publishedOn": "2023-02-06T17:46:52.000Z",
          "wordCount": 492,
          "title": "Binance to temporarily suspend US dollar bank transfers starting on Wednesday...",
          "imageUrl": null
        },
        {
          "id": "https://twitter.com/defipulse/status/1622652447616270361",
          "author": "DeFi Pulse",
          "description": "Re  https://www.coindesk.com/business/2023/02/06/bankrupt-lender-genesis-and-parent-dcg-reach-initial-agreement-with-main-creditors-source/",
          "link": "https://twitter.com/defipulse/status/1622652447616270361",
          "publishedOn": "2023-02-06T17:44:25.000Z",
          "wordCount": 492,
          "title": "Re",
          "imageUrl": null
        },
        {
          "id": "https://twitter.com/defipulse/status/1622652445217128465",
          "author": "DeFi Pulse",
          "description": "Genesis and parent DCG reach an initial agreement with main creditors...",
          "link": "https://twitter.com/defipulse/status/1622652445217128465",
          "publishedOn": "2023-02-06T17:44:25.000Z",
          "wordCount": 492,
          "title": "Genesis and parent DCG reach an initial agreement with main creditors...",
          "imageUrl": null
        },
        {
          "id": "https://twitter.com/defipulse/status/1622624204234317825",
          "author": "DeFi Pulse",
          "description": "Re  https://blockworks.co/news/visa-eyes-high-value-usdc-settlement-payments-on-ethereum",
          "link": "https://twitter.com/defipulse/status/1622624204234317825",
          "publishedOn": "2023-02-06T15:52:11.000Z",
          "wordCount": 492,
          "title": "Re",
          "imageUrl": null
        },
        {
          "id": "https://twitter.com/defipulse/status/1622624202275553280",
          "author": "DeFi Pulse",
          "description": "Visa testing USDC settlement payments on Ethereum...",
          "link": "https://twitter.com/defipulse/status/1622624202275553280",
          "publishedOn": "2023-02-06T15:52:11.000Z",
          "wordCount": 492,
          "title": "Visa testing USDC settlement payments on Ethereum...",
          "imageUrl": null
        }
      ]
    }
  ],
  "cliVersion": "1.15.1"
}