{
  "sources": [
    {
      "title": "Twitter @DeFi Pulse 🍇",
      "feedUrl": "https://rsshub.app/twitter/user/defipulse",
      "siteUrl": "https://twitter.com/defipulse",
      "articles": [
        {
          "id": "https://twitter.com/sassal0x/status/1523813695620411392",
          "author": "DeFi Pulse 🍇",
          "description": "RT sassal.eth 🦇🔊🐼\nDecentralization matters",
          "link": "https://twitter.com/sassal0x/status/1523813695620411392",
          "publishedOn": "2022-05-09T23:54:30.000Z",
          "wordCount": 196,
          "title": "RT sassal.eth 🦇🔊🐼: Decentralization matters",
          "imageUrl": null
        },
        {
          "id": "https://twitter.com/defipulse/status/1523811681163673600",
          "author": "DeFi Pulse 🍇",
          "description": "Re @alexeiZamyatin @InterlayHQ If a stable needs another protocol to do its primary job right... something sound wrong.\nOf course no problem at all with Interlay.",
          "link": "https://twitter.com/defipulse/status/1523811681163673600",
          "publishedOn": "2022-05-09T23:46:30.000Z",
          "wordCount": 196,
          "title": "Re @alexeiZamyatin @InterlayHQ If a stable needs another protocol to do its primary job right... something sound wrong. Of course no problem at all wi...",
          "imageUrl": null
        },
        {
          "id": "https://twitter.com/defipulse/status/1523802903860764672",
          "author": "DeFi Pulse 🍇",
          "description": "Re 13/ \nIf this thread helped you to understand recent concerns and discussions about $UST and stablecoins in general, like it and share!",
          "link": "https://twitter.com/defipulse/status/1523802903860764672",
          "publishedOn": "2022-05-09T23:11:37.000Z",
          "wordCount": 196,
          "title": "Re 13/ If this thread helped you to understand recent concerns and discussions about $UST and stablecoins in general, like it and share!",
          "imageUrl": null
        },
        {
          "id": "https://twitter.com/defipulse/status/1523802883765940224",
          "author": "DeFi Pulse 🍇",
          "description": "Re 12/ Decentralized algorithm, centralized collateral 👀\nThe algorithm that controls $UST is decentralized, but the $BTC reserve “in case something goes wrong” is controlled by an entity.\nBecause of recent volatility, they've announced a $1.5B deployment.\nDo Kwon 🌕: 2/ First, *LFG is not trying to exit its bitcoin position*. \nThe goal is to have this capital in the hands of a professional market maker such that: \n1) Buy UST if price < peg\n2) Buy BTC if price >= peg\nthus significantly strengthening the liquidity around UST peg",
          "link": "https://twitter.com/defipulse/status/1523802883765940224",
          "publishedOn": "2022-05-09T23:11:33.000Z",
          "wordCount": 196,
          "title": "Re 12/ Decentralized algorithm, centralized collateral 👀 The algorithm that controls $UST is decentralized, but the $BTC reserve “in case somethin...",
          "imageUrl": null
        },
        {
          "id": "https://twitter.com/defipulse/status/1523802880888631296",
          "author": "DeFi Pulse 🍇",
          "description": "Re 11/ Decentralized and unbiased\nMaker's vaults are controlled by smart-contracts. The collateral management, liquidation process, price checks, everything is decentralized. Emergency processes can be triggered by the DAO, a decentralized entity.\nWhat about $UST?",
          "link": "https://twitter.com/defipulse/status/1523802880888631296",
          "publishedOn": "2022-05-09T23:11:32.000Z",
          "wordCount": 196,
          "title": "Re 11/ Decentralized and unbiased Maker's vaults are controlled by smart-contracts. The collateral management, liquidation process, price checks, ever...",
          "imageUrl": null
        },
        {
          "id": "https://twitter.com/defipulse/status/1523802878019706881",
          "author": "DeFi Pulse 🍇",
          "description": "Re 10/ Collateral-backed\nEach $DAI in circulation is backed by a diverse class of cryptoassets. If your vault collateralization drops from a certain amount (from 130 to 150%) you're liquidated.\n$UST peg is maintained by an algorithm, but there is a $BTC reserve in case it fails.",
          "link": "https://twitter.com/defipulse/status/1523802878019706881",
          "publishedOn": "2022-05-09T23:11:31.000Z",
          "wordCount": 196,
          "title": "Re 10/ Collateral-backed Each $DAI in circulation is backed by a diverse class of cryptoassets. If your vault collateralization drops from a certain a...",
          "imageUrl": null
        },
        {
          "id": "https://twitter.com/defipulse/status/1523802874815279104",
          "author": "DeFi Pulse 🍇",
          "description": "Re 9/ With that risk in mind, the Luna Foundation Guard had raised over $1B through private token sales to build a crypto reserve to support $UST. \nSo now the algo stable is also… collateralized? 🤔\nLet's recap $DAI's main features and compare with $UST.\nLFG | Luna Foundation Guard: Welcoming $AVAX as the second major layer one crypto asset next to $BTC as part of the $UST Reserve. \nThe inclusion of @avalancheavax's native token marks the start of a diverse pool of layer one crypto assets helping support the $UST peg. \nIt's only just the beginning frens.\n https://twitter.com/business/status/1512110339613147142",
          "link": "https://twitter.com/defipulse/status/1523802874815279104",
          "publishedOn": "2022-05-09T23:11:30.000Z",
          "wordCount": 196,
          "title": "Re 9/ With that risk in mind, the Luna Foundation Guard had raised over $1B through private token sales to build a crypto reserve to support $UST. So ...",
          "imageUrl": null
        },
        {
          "id": "https://twitter.com/defipulse/status/1523802871841497088",
          "author": "DeFi Pulse 🍇",
          "description": "Re 8/ As we've experienced before with $FEI, a Black Swan event or just a strong bearish sentiment could cause a large sell pressure on both $UST and $LUNA assets, causing a \"death spiral\".\nWestie 🌖 🟪: This process is what is known as a \"bank run\" or a \"death spiral,\" and can be visualized below. (Source: @ZeMariaMacedo",
          "link": "https://twitter.com/defipulse/status/1523802871841497088",
          "publishedOn": "2022-05-09T23:11:30.000Z",
          "wordCount": 196,
          "title": "Re 8/ As we've experienced before with $FEI, a Black Swan event or just a strong bearish sentiment could cause a large sell pressure on both $UST and ...",
          "imageUrl": null
        },
        {
          "id": "https://twitter.com/defipulse/status/1523802868632805376",
          "author": "DeFi Pulse 🍇",
          "description": "Re 7/ Collateralized x Algorithmic\nThis is where both solutions differentiate the most. While Maker protocol holds a higher amount of dollars in cryptoassets than $DAI in circulation, $UST relies on human reaction facing supply/demands fluctuation.\nBut humans are not perfect.",
          "link": "https://twitter.com/defipulse/status/1523802868632805376",
          "publishedOn": "2022-05-09T23:11:29.000Z",
          "wordCount": 196,
          "title": "Re 7/ Collateralized x Algorithmic This is where both solutions differentiate the most. While Maker protocol holds a higher amount of dollars in crypt...",
          "imageUrl": null
        },
        {
          "id": "https://twitter.com/defipulse/status/1523802856955863041",
          "author": "DeFi Pulse 🍇",
          "description": "Re 6/ To implement the elastic supply mechanism, Terra uses its governance coin, $LUNA.\nIn the Terra Blockchain, users can always swap $1 worth of $LUNA to 1 $UST and vice-versa, incentivizing arbitrageurs to take action in case the peg is lost.",
          "link": "https://twitter.com/defipulse/status/1523802856955863041",
          "publishedOn": "2022-05-09T23:11:26.000Z",
          "wordCount": 196,
          "title": "Re 6/ To implement the elastic supply mechanism, Terra uses its governance coin, $LUNA. In the Terra Blockchain, users can always swap $1 worth of $LU...",
          "imageUrl": null
        },
        {
          "id": "https://twitter.com/defipulse/status/1523802850102448129",
          "author": "DeFi Pulse 🍇",
          "description": "Re 5/  When writing an algorithm for a stablecoin, projects usually try to work with variations of a demand/supply mechanisms.  \nIt's intuitive if u think about it: if the coin drops in price, let's burn some of it, creating a shortage of supply. But $UST adds some details.",
          "link": "https://twitter.com/defipulse/status/1523802850102448129",
          "publishedOn": "2022-05-09T23:11:25.000Z",
          "wordCount": 196,
          "title": "Re 5/ When writing an algorithm for a stablecoin, projects usually try to work with variations of a demand/supply mechanisms. It's intuitive if u thin...",
          "imageUrl": null
        },
        {
          "id": "https://twitter.com/defipulse/status/1523802843643142144",
          "author": "DeFi Pulse 🍇",
          "description": "Re 4/ And what is $UST?\n$UST is an algorithmically stabilized cryptocurrency. \n It means that its peg (in this case to USD) is maintained by calculations executed by a smart-contract. There are many different algorithms for maintaining stablecoins, let's dive into $UST's.",
          "link": "https://twitter.com/defipulse/status/1523802843643142144",
          "publishedOn": "2022-05-09T23:11:23.000Z",
          "wordCount": 196,
          "title": "Re 4/ And what is $UST? $UST is an algorithmically stabilized cryptocurrency. It means that its peg (in this case to USD) is maintained by calculation...",
          "imageUrl": null
        },
        {
          "id": "https://twitter.com/defipulse/status/1523802829911076864",
          "author": "DeFi Pulse 🍇",
          "description": "Re 3/  Collateral-backed: \nEach $DAI put into circulation is backed by different class of cryptocurrency as $ETH, $WBTC, $UNI and others decided by the DAO.  \nThe stable is overcollateralized, meaning that you can mint less $DAI than the relative value of collateral locked.",
          "link": "https://twitter.com/defipulse/status/1523802829911076864",
          "publishedOn": "2022-05-09T23:11:20.000Z",
          "wordCount": 196,
          "title": "Re 3/ Collateral-backed: Each $DAI put into circulation is backed by different class of cryptocurrency as $ETH, $WBTC, $UNI and others decided by the ...",
          "imageUrl": null
        },
        {
          "id": "https://twitter.com/defipulse/status/1523802822772285440",
          "author": "DeFi Pulse 🍇",
          "description": "Re 2/  Decentralized and unbiased \n$DAI is not controlled by any centralized entity. The stablecoin is maintained by the Maker Protocol trough @oasisdotapp, with collaboration of the @MakerDAO governance.\nLearn more about Oasis 👇 https://www.defipulse.com/blog/oasis-app-growing-cryptos-tried-and-true-dai-and-defi-gateway",
          "link": "https://twitter.com/defipulse/status/1523802822772285440",
          "publishedOn": "2022-05-09T23:11:18.000Z",
          "wordCount": 196,
          "title": "Re 2/ Decentralized and unbiased $DAI is not controlled by any centralized entity. The stablecoin is maintained by the Maker Protocol trough @oasisdot...",
          "imageUrl": null
        },
        {
          "id": "https://twitter.com/defipulse/status/1523802819886604288",
          "author": "DeFi Pulse 🍇",
          "description": "Re 1/  What is $DAI? \n\"Dai is a decentralized, unbiased, collateral-backed cryptocurrency soft-pegged to the US Dollar\" - according to Maker's Whitepaper. \nBut what does each one of those terms mean? https://makerdao.com/en/whitepaper#abstract",
          "link": "https://twitter.com/defipulse/status/1523802819886604288",
          "publishedOn": "2022-05-09T23:11:17.000Z",
          "wordCount": 196,
          "title": "Re 1/ What is $DAI? \"Dai is a decentralized, unbiased, collateral-backed cryptocurrency soft-pegged to the US Dollar\" - according to Maker's Whitepape...",
          "imageUrl": null
        },
        {
          "id": "https://twitter.com/defipulse/status/1523802816657035264",
          "author": "DeFi Pulse 🍇",
          "description": "What are the main differences between $DAI (a decentralized stablecoin on Ethereum) and $UST (Terra's algo stablecoin)?\nLet's find out! (1/13) 🧵",
          "link": "https://twitter.com/defipulse/status/1523802816657035264",
          "publishedOn": "2022-05-09T23:11:17.000Z",
          "wordCount": 196,
          "title": "What are the main differences between $DAI (a decentralized stablecoin on Ethereum) and $UST (Terra's algo stablecoin)? Let's find out! (1/13) 🧵",
          "imageUrl": null
        },
        {
          "id": "https://twitter.com/defipulse/status/1523748971096592384",
          "author": "DeFi Pulse 🍇",
          "description": "🚨BREAKING: Luna Foundation Guard's (LFG) wallet moved over 42 thousand #Bitcoin = $1.3B https://www.blockchain.com/btc/address/bc1q9d4ywgfnd8h43da5tpcxcn6ajv590cg6d3tg6axemvljvt2k76zs50tv4q",
          "link": "https://twitter.com/defipulse/status/1523748971096592384",
          "publishedOn": "2022-05-09T19:37:19.000Z",
          "wordCount": 196,
          "title": "🚨BREAKING: Luna Foundation Guard's (LFG) wallet moved over 42 thousand #Bitcoin = $1.3B",
          "imageUrl": null
        },
        {
          "id": "https://twitter.com/defipulse/status/1523743170542022661",
          "author": "DeFi Pulse 🍇",
          "description": "Re @nayibbukele President doing DCA?",
          "link": "https://twitter.com/defipulse/status/1523743170542022661",
          "publishedOn": "2022-05-09T19:14:16.000Z",
          "wordCount": 196,
          "title": "Re @nayibbukele President doing DCA?",
          "imageUrl": null
        },
        {
          "id": "https://twitter.com/defipulse/status/1523741788795596801",
          "author": "DeFi Pulse 🍇",
          "description": "What are your thoughts? 👀\n$UST = $0.95 \nDo you think the peg can be established?",
          "link": "https://twitter.com/defipulse/status/1523741788795596801",
          "publishedOn": "2022-05-09T19:08:46.000Z",
          "wordCount": 196,
          "title": "What are your thoughts? 👀 $UST = $0.95 Do you think the peg can be established?",
          "imageUrl": null
        },
        {
          "id": "https://twitter.com/defipulse/status/1523693160035086340",
          "author": "DeFi Pulse 🍇",
          "description": "Re This is a sneak peak of how it will look:",
          "link": "https://twitter.com/defipulse/status/1523693160035086340",
          "publishedOn": "2022-05-09T15:55:32.000Z",
          "wordCount": 196,
          "title": "Re This is a sneak peak of how it will look:",
          "imageUrl": null
        }
      ]
    }
  ],
  "cliVersion": "1.14.4"
}